odoo9_addon_account_bank_statement_import_camt_details-9.0.1.0.0-py2.7-nspkg.pth
odoo9_addon_account_bank_statement_import_camt_details-9.0.1.0.0.dist-info/DESCRIPTION.rst
odoo9_addon_account_bank_statement_import_camt_details-9.0.1.0.0.dist-info/METADATA
odoo9_addon_account_bank_statement_import_camt_details-9.0.1.0.0.dist-info/RECORD
odoo9_addon_account_bank_statement_import_camt_details-9.0.1.0.0.dist-info/WHEEL
odoo9_addon_account_bank_statement_import_camt_details-9.0.1.0.0.dist-info/metadata.json
odoo9_addon_account_bank_statement_import_camt_details-9.0.1.0.0.dist-info/namespace_packages.txt
odoo9_addon_account_bank_statement_import_camt_details-9.0.1.0.0.dist-info/top_level.txt
odoo_addons/account_bank_statement_import_camt_details/README.rst
odoo_addons/account_bank_statement_import_camt_details/__init__.py
odoo_addons/account_bank_statement_import_camt_details/__openerp__.py
odoo_addons/account_bank_statement_import_camt_details/models/__init__.py
odoo_addons/account_bank_statement_import_camt_details/models/account_bank_statement_line.py
odoo_addons/account_bank_statement_import_camt_details/models/camt_parser.py
odoo_addons/account_bank_statement_import_camt_details/static/src/xml/camt_details_reconciliation_layout.xml
odoo_addons/account_bank_statement_import_camt_details/tests/__init__.py
odoo_addons/account_bank_statement_import_camt_details/tests/test_import_bank_statement.py
odoo_addons/account_bank_statement_import_camt_details/views/account_bank_statement_line.xml
