Metadata-Version: 2.0
Name: odoo9-addon-account-bank-statement-import-camt-details
Version: 9.0.1.0.0
Summary: CAMT Debitor Details Bank Statements Import
Home-page: https://github.com/OCA/bank-statement-import
Author: Odoo Community Association (OCA), Compassion CH
Author-email: support@odoo-community.org
License: AGPL-3
Platform: UNKNOWN
Classifier: Programming Language :: Python :: 2.7
Classifier: Framework :: Odoo
Classifier: License :: OSI Approved :: GNU Affero General Public License v3
Requires-Dist: odoo (<9.1a,>=9.0a)
Requires-Dist: odoo9-addon-account-bank-statement-import-camt
